Q5_semaforo/SEMAFORO.v
module Semaforo(
    input CAR, TIMEOUT, clk,
    output reg GRN, YLW, RED);

    parameter GREENSTATE   = 2'b00;
    parameter YELLOWSTATE  = 2'b01;
    parameter REDSTATE     = 2'b10;

    reg [1:0] state, next_state;

    always @(posedge clk) 
    begin
        state <= next_state;
    end

    always @(*)
    begin
        case(state)
            GREENSTATE: begin
                if (CAR) next_state = YELLOWSTATE;
                else     next_state = GREENSTATE;
            end
            YELLOWSTATE: begin
                next_state = REDSTATE;
            end
            REDSTATE: begin
                if (TIMEOUT) next_state = GREENSTATE;
                else          next_state = REDSTATE;
            end
            default: next_state = GREENSTATE;
        endcase
    end

    always @(*) 
    begin
        case(state)
            GREENSTATE:
                begin
                    GRN = 1'b1;
                    YLW = 1'b0;
                    RED = 1'b0;
                end
            YELLOWSTATE:
                begin
                    GRN = 1'b0;
                    YLW = 1'b1;
                    RED = 1'b0;
                end
            REDSTATE:
                begin
                    GRN = 1'b0;
                    YLW = 1'b0;
                    RED = 1'b1;
                end
            default:
                begin
                    GRN = 1'b0;
                    YLW = 1'b0;
                    RED = 1'b0;
                end
        endcase
    end
endmodule

Q5_semaforoestrutural/SEMAFORO_tb.v
`include "SEMAFORO.v"

module tb_Semaforo;

    
    reg CAR;
    reg TIMEOUT;
    reg clk;
    

    wire GRN;
    wire YLW;
    wire RED;

  
    Semaforo uut (
        .CAR(CAR),
        .TIMEOUT(TIMEOUT),
        .clk(clk),
        .GRN(GRN),
        .YLW(YLW),
        .RED(RED)
    );

   
    always begin
        #5 clk = ~clk; 
    end

    initial begin
  
        clk = 0;
        CAR = 0;
        TIMEOUT = 0;
        $dumpfile("semaforo.vcd"); 
        $dumpvars(0, tb_Semaforo);

 
        $display("Iniciando a simulação");

        #10;
        $display("Estado inicial: GRN = %b, YLW = %b, RED = %b", GRN, YLW, RED);

        // Teste 2: Ativando o CAR e verificando transição para amarelo
        CAR = 1; // Detector de carro ativado
        #10;
        $display("Após CAR ativado: GRN = %b, YLW = %b, RED = %b", GRN, YLW, RED);

        // Teste 3: Semáforo deve transitar para vermelho
        CAR = 0;
        #10;
        $display("Após transição para VERMELHO: GRN = %b, YLW = %b, RED = %b", GRN, YLW, RED);

        // Teste 4: Semáforo em vermelho
        #10;
        $display("Semáforo em VERMELHO: GRN = %b, YLW = %b, RED = %b", GRN, YLW, RED);

        // Teste 5: Timeout ativado, semáforo deve voltar para verde
        TIMEOUT = 1; // Timeout após 15 segundos
        #10;
        $display("Após TIMEOUT: GRN = %b, YLW = %b, RED = %b", GRN, YLW, RED);

        // Teste 6: Semáforo deve ficar verde
        #10;
        $display("Semáforo em VERDE: GRN = %b, YLW = %b, RED = %b", GRN, YLW, RED);

        // Finaliza a simulação
        $finish;
    end

endmodule

Q5_semaforo/semaforo.vcd
$date
	Sun Mar 16 19:16:34 2025
$end
$version
	Icarus Verilog
$end
$timescale
	1s
$end
$scope module tb_Semaforo $end
$var wire 1 ! YLW $end
$var wire 1 " RED $end
$var wire 1 # GRN $end
$var reg 1 $ CAR $end
$var reg 1 % TIMEOUT $end
$var reg 1 & clk $end
$scope module uut $end
$var wire 1 $ CAR $end
$var wire 1 % TIMEOUT $end
$var wire 1 & clk $end
$var parameter 2 ' GREENSTATE $end
$var parameter 2 ( REDSTATE $end
$var parameter 2 ) YELLOWSTATE $end
$var reg 1 # GRN $end
$var reg 1 " RED $end
$var reg 1 ! YLW $end
$var reg 2 * next_state [1:0] $end
$var reg 2 + state [1:0] $end
$upscope $end
$upscope $end
$enddefinitions $end
$comment Show the parameter values. $end
$dumpall
b1 )
b10 (
b0 '
$end
#0
$dumpvars
bx +
b0 *
0&
0%
0$
x#
x"
x!
$end
#5
0"
0!
1#
b0 +
1&
#10
b1 *
0&
1$
#15
1!
0#
b10 *
b1 +
1&
#20
0&
0$
#25
1"
0!
b10 +
1&
#30
0&
#35
1&
#40
b0 *
0&
1%
#45
0"
1#
b0 +
1&
